{
  "017": {
    "name": "㈱エステーリンク",
    "sources": [
      "work-bench_p01.png",
      "work-bench_p02.png",
      "メタルスライダー600_MS0601_26.03_WEB用_p01.png",
      "メタルスライダー600_MS0601_26.03_WEB用_p02.png"
    ],
    "sections": [
      {
        "title": "siegmund ワークベンチセット",
        "subtitle": "テーブル全面でワークを固定／溶接スパッタが付着しづらい／テーブル高さは調整可能",
        "table_columns": ["項目", "仕様"],
        "table": [
          {"項目": "作業プレート面積", "仕様": "1200×800×12 (mm) ※側面穴なし"},
          {"項目": "材質および表面処理", "仕様": "高品質鋼＋プラズマ窒化処理"},
          {"項目": "プレート穴ピッチ", "仕様": "50mm×50mmピッチ"},
          {"項目": "作業台高さ", "仕様": "800mm～950mm"},
          {"項目": "フレーム", "仕様": "アルミニウム"},
          {"項目": "耐荷重", "仕様": "250kg"}
        ],
        "highlights": [
          "ドイツSiegmund社 溶接作業用3D定盤の日本代理店",
          "テーブル全面でワークを即席治具で固定可能（専用ボルト・アングル・クランプ利用）",
          "溶接スパッタの溶着を防ぐ特殊な窒化処理を表面に施した高品質鋼を採用",
          "テーブル高さは800〜950mm・50mmピッチで調整、立ち姿勢でも作業しやすい",
          "サイドエクステンションでワークベンチを連結、理想の作業スペースを構築可能"
        ],
        "warnings": [
          "別売オプション（引き出し／ツールホルダー／キャスター）は取寄せとなります"
        ],
        "new_models": [],
        "accessories": [
          {"品番": "160108.A・160109.A", "内容": "角度固定アングル90° 各4本ずつ"},
          {"品番": "160621", "内容": "スクリュークランプ 4本"},
          {"品番": "160511", "内容": "クランピングボルト 8本"}
        ],
        "options": [
          "オプション①: 引き出し",
          "オプション②: ツールホルダー",
          "オプション③: キャスター",
          "サイドエクステンション装着例"
        ]
      },
      {
        "title": "METAL-SLIDER 600 メタルスライダー",
        "subtitle": "板金屋が追及した板金屋のための“高剛性＆省スペース型”バリ取り機 (型番: MS0601 / 2026年新発売！)",
        "table_columns": ["項目", "仕様"],
        "table": [
          {"項目": "型式", "仕様": "MS0601"},
          {"項目": "最大ワーク幅", "仕様": "600mm"},
          {"項目": "最大ワーク厚さ", "仕様": "100mm"},
          {"項目": "機械寸法", "仕様": "—"},
          {"項目": "機械重量", "仕様": "1100kg"},
          {"項目": "電源", "仕様": "AC200V 3φ"},
          {"項目": "周波数", "仕様": "50/60Hz"},
          {"項目": "電気容量", "仕様": "5.4kW"}
        ],
        "highlights": [
          "業界初！集塵機内蔵 バリ取り機（省スペース×高剛性×パワフル研磨）",
          "手作業のバリ取りから作業時間最大95%減！圧倒的バリ取り効率",
          "設置面積従来比30%減、集塵機内蔵型で工場レイアウトの自由度も向上",
          "自動基点設定で加工前の設定が簡単に。光軸検知センサー搭載で板厚自動補正",
          "ダブル研磨方式（ノロ・ドロスまでをバリプロ研磨と同時に除去）"
        ],
        "warnings": [
          "対応素材・加工事例詳細はST-LiNK社まで問い合わせのこと"
        ],
        "new_models": [
          {"model": "MS0601 メタルスライダー600", "note": "2026年新発売 / 業界初の集塵機内蔵バリ取り機"}
        ],
        "abrasive_tools": [
          "標準研磨ブラシ（クイックリリース機能で交換容易）",
          "サンディングシート＋バリ取り用",
          "ヒーローブラシ（研削力強化、角R付）",
          "ワイヤーブラシ（強力磁性物質除去）",
          "ピンブラシ（ドロス除去用）"
        ],
        "options": [
          "シグナルタワー（安全に配慮したスイッチの追加。ブザーの追加、緑の設置音もあり）",
          "リターンコンベア（バリ取り後のワークの戻しに便利）",
          "粉塵除去装置（バリ取り後の粉塵をリターンコンベア上の特殊ブラシで除去）"
        ]
      }
    ]
  },
  "040": {
    "name": "酸素アーク工業㈱",
    "sources": [
      "チラシ3点BX_9-5L_オクトギア_p01.png",
      "チラシ3点BX_9-5L_オクトギア_p02.png",
      "チラシ3点BX_9-5L_オクトギア_p03.png"
    ],
    "sections": [
      {
        "title": "シャーブランス SC2-6BX",
        "subtitle": "鋼管杭・シートパイルなどの溶断、穿孔に！",
        "table_columns": ["品番", "外径(mm)", "内径(mm)", "全長(mm)", "重量(kg/本)", "酸素流量(N㎥/min)"],
        "table": [
          {"品番": "SC2-6BX", "外径(mm)": "12.7", "内径(mm)": "—", "全長(mm)": "1,850", "重量(kg/本)": "1.30", "酸素流量(N㎥/min)": "0.59〜0.78"}
        ],
        "highlights": [
          "鋼管杭・シートパイルの溶断や穿孔作業に最適なシャーブランス",
          "鋼管杭1,000mmφ切断（内壁裏当て構材）で20〜30分・3〜4本使用",
          "下水道のシートパイル2型切断（裏返し時除く）で5分・3.5本使用",
          "推進工法のシートパイル2型切断（裏返し時除く）約8224mmを30分・4本で切断"
        ],
        "warnings": [],
        "new_models": [],
        "accessories": [
          {"品番": "MT 150", "name": "シャーブランスホルダー", "note": "ホルダーケーブル長 7.5m (60BX用)"}
        ],
        "use_cases": [
          {"用途": "①鋼管杭1,000mmφ切断（内壁裏当て構材）", "切断時間": "20〜30分", "切断棒使用本数": "3〜4本", "酸素使用本数": "（7000L/L 0.7〜0.8本／鋼管杭1本）"},
          {"用途": "②下水道のシートパイル2型切断（裏返し時除く）", "切断時間": "20分", "シートパイル枚数": "10枚", "酸素使用本数": "3.5本"},
          {"用途": "③推進工法のシートパイル2型切断（裏返し時除く）", "切断長さ": "約8224mm", "切断時間": "30分", "切断棒使用本数": "4本", "酸素使用本数": "（7000L/L 0.7本）"}
        ]
      },
      {
        "title": "スターカッテンド SC9-5L",
        "subtitle": "鋼管杭・シートパイルなどの溶断、穿孔に！（AC/DC Welder接続式）",
        "table_columns": ["品番", "外径(mm)", "全長(mm)", "重量(kg/本)", "酸素流量(N㎥/min)"],
        "table": [
          {"品番": "SC9-5L", "外径(mm)": "9.0", "全長(mm)": "900", "重量(kg/本)": "0.38", "酸素流量(N㎥/min)": "0.5〜0.6"}
        ],
        "highlights": [
          "ガソリンエンジン発電機（AC/DC Welder）接続式のスターカッテンド",
          "鋼管杭1,000mmφ切断（内装裏当て構材）で17〜19分・15〜17本使用",
          "下水道シートパイル17〜19枚切断を13〜15本／20分で実施",
          "推進工法シートパイル切断 約8224mmを17〜19分・15〜17本で切断"
        ],
        "warnings": [
          "氷水温度においての使用はおやめください",
          "オプションとして「SR9-600」「SR9-900」があります"
        ],
        "new_models": [],
        "accessories": [
          {"品番": "KT 89", "name": "スターカッテンドホルダー", "note": "キャブタイヤケーブル付"}
        ],
        "use_cases": [
          {"用途": "①鋼管杭1,000mmφ切断（内装裏当て構材）", "切断時間": "17〜19分", "切断棒使用本数": "15〜17本", "酸素使用本数": "（7000L/L 0.7本／鋼管杭1本）"},
          {"用途": "②下水道のシートパイル切断", "切断時間": "20分", "シートパイル枚数": "17〜19枚", "酸素使用本数": "13〜15本"},
          {"用途": "③推進工法のシートパイル2型切断（裏返し時除く）", "切断長さ": "8224mm", "切断時間": "17〜19分", "切断棒使用本数": "15〜17本", "酸素使用本数": "（7000L/L 0.7本）"}
        ]
      },
      {
        "title": "新世代シャーブランス オクトギア OCTO-GEAR",
        "subtitle": "熔断酸素流の「強力な推進力」と「鋭い集中性」を実現。（特許出願中）",
        "table_columns": [],
        "table": [],
        "highlights": [
          "従来の酸素溶断棒は数本の鉄鋼線材を熔加材として使用しているが、熔加材がパイプの中央に集まり次第に熔加材の乱れが原因で酸素流の乱れが原因で溶断作業の不規則性が発生。「オクトギア」は熔加材の整列構造を実現",
          "強力な熔断力 — 酸素流に乱れがなく、二進化した熔加材の高熱化で集中性が向上",
          "熔断作業時間の短縮 — 「オクトギア」の溶断スピードの向上を実現、作業コストダウンが実感",
          "シャープな熔断面 — 「オクトギア」のシャープなEDGEで熔断精度向上",
          "ランス棒燃焼時の煙の減少 — 酸素流量と「オクトギア」の溶加材の特性により煙の発生量を削減",
          "酸素消費量の低減 — 一定の溶断作業に対し「オクトギア」の溶加材の特性で必要な少ない酸素消費量で溶断作業可能"
        ],
        "warnings": [
          "酸素溶断棒の溶断力はどれも同じと思っていませんか？シャーブランス「オクトギア」は全く違うんです！「オクトギア」は、まさにランス棒（酸素溶断棒）の五ツ星！！"
        ],
        "new_models": [
          {"model": "オクトギア OCTO-GEAR", "note": "新世代シャーブランス・特許出願中"}
        ]
      }
    ]
  },
  "100": {
    "name": "㈱ハタヤリミテッド",
    "sources": [
      "2026TWFチラシ表_p01.png",
      "2026TWFチラシ裏_p01.png"
    ],
    "sections": [
      {
        "title": "ハタヤリミテッド目玉製品",
        "subtitle": "2026東京ウェルディングフェスタ 特価品",
        "table_columns": ["型式", "製品名", "全光束/出力", "標準価格(税抜)", "特価(税抜)"],
        "table": [
          {"型式": "LWA-50KHBN-M", "製品名": "50W LEDケイ・ライト ハイブリッドマグネット付", "全光束/出力": "AC点灯5,500lm／バッテリー点灯2,000lm", "標準価格(税抜)": "¥53,600", "特価(税抜)": "¥32,000"},
          {"型式": "LTP-10TDS", "製品名": "温度センサー付LEDテープライト（両面発光）", "全光束/出力": "1,200lm（新発売）", "標準価格(税抜)": "¥83,000", "特価(税抜)": "¥52,000"}
        ],
        "highlights": [
          "100Vでもバッテリーでも使える ハイブリッド仕様（バッテリー点灯6時間）",
          "ケーブルが脱着できるのでバッテリー点灯時の取り回しが楽！",
          "IP55／マグネット、バイス、フック対応で現場で頼れる据え付け性",
          "安全第一！温度センサー付LEDテープライトでテープライト本体の温度上昇を温度センサーが感知し焼損を防ぎます！"
        ],
        "warnings": [],
        "new_models": [
          {"model": "LTP-10TDS", "note": "新発売 / 温度センサー付LEDテープライト 両面発光 1,200lm"}
        ]
      },
      {
        "title": "大特価おすすめ製品！",
        "subtitle": "2026東京ウェルディングフェスタ 裏面特価品",
        "table_columns": ["型番", "製品名", "全光束/特徴", "標準価格(税抜)", "特価(税抜)"],
        "table": [
          {"型番": "LLA-120K", "製品名": "120W LEDボールライト", "全光束/特徴": "12,000lm／故障が少ないファンレス構造（爆売れ！）", "標準価格(税抜)": "¥151,200", "特価(税抜)": "¥63,000"},
          {"型番": "LEF-M200KO", "製品名": "軽量200W LED投光器", "全光束/特徴": "26,000lm／調光付／180度に広く照らす／防雨型／自立できる", "標準価格(税抜)": "¥213,300", "特価(税抜)": "¥79,800"},
          {"型番": "LLA-30K", "製品名": "80W LEDボールライト", "全光束/特徴": "8,000lm／小型で持ち運びが楽！", "標準価格(税抜)": "¥115,200", "特価(税抜)": "¥39,800"},
          {"型番": "LHAL-01NC", "製品名": "LEDヘッドネスアタッチメントライト", "全光束/特徴": "全光束（最大）500lm／4時間／ネック、グリットマウントアタッチメント付属", "標準価格(税抜)": "¥12,600", "特価(税抜)": "¥8,900"}
        ],
        "highlights": [
          "120W LEDボールライトは故障が少ないファンレス構造で爆売れ中",
          "軽量200W LED投光器は26,000lm調光付で180度に広く照らす、防雨型・自立対応",
          "80W LEDボールライトは小型で持ち運びが楽、現場間移動が多い職人の味方",
          "LEDヘッドネスアタッチメントライトは最大500lm／4時間・ネック・グリットマウント付属"
        ],
        "warnings": [],
        "new_models": []
      }
    ]
  },
  "132": {
    "name": "柳瀬㈱",
    "sources": [
      "2026東京ウェルディングフェスタ_p01.png",
      "2026東京ウェルディングフェスタ_p02.png"
    ],
    "sections": [
      {
        "title": "ベルトサンダー・マイディシリーズ 2台目半額！！",
        "subtitle": "SALE期間: 本日〜6月30日 ／ 会場: 幕張メッセ ／ 開催日: 2026年6/12（金）〜6/13（土）",
        "table_columns": ["型番", "製品名", "回転数", "ベルトサイズ／砥石", "使用ベルト幅", "全長", "質量", "セール価格(税抜)"],
        "table": [
          {"型番": "MTM-AT60S", "製品名": "マイディミニ ATS", "回転数": "7,000min⁻¹", "ベルトサイズ／砥石": "200×40mm", "使用ベルト幅": "—", "全長": "—", "質量": "1.4kg", "セール価格(税抜)": "¥43,000"},
          {"型番": "MTM-ET60S", "製品名": "マイディミニ ETS", "回転数": "6,500min⁻¹", "ベルトサイズ／砥石": "—", "使用ベルト幅": "200mm幅対応", "全長": "—", "質量": "1.8kg", "セール価格(税抜)": "¥43,000"},
          {"型番": "AGBS-10-2", "製品名": "ベルトサンダー10", "回転数": "16,000min⁻¹", "ベルトサイズ／砥石": "10×330mm", "使用ベルト幅": "10mm", "全長": "—", "質量": "0.94kg", "セール価格(税抜)": "¥30,000"},
          {"型番": "AGBS-20-2", "製品名": "ベルトサンダー20", "回転数": "16,000min⁻¹", "ベルトサイズ／砥石": "20×520mm", "使用ベルト幅": "20mm", "全長": "—", "質量": "0.98kg", "セール価格(税抜)": "¥34,000"},
          {"型番": "AGSS-ST2", "製品名": "ダイグラインダー2", "回転数": "23,000min⁻¹", "ベルトサイズ／砥石": "コレット6mm", "使用ベルト幅": "—", "全長": "175mm", "質量": "0.46kg", "セール価格(税抜)": "¥12,000"}
        ],
        "highlights": [
          "2台目半額！！キャンペーン — 大幅値引きで高性能ベルトサンダーを揃えるチャンス",
          "マイディミニ ATS／ETS 各¥43,000、エアパワフル＆軽量で長時間作業も安心",
          "ベルトサンダー10/20 ＋ ハッピーベルト 10×330mm 50本セットでお得！¥32,000",
          "#40 #60 #80 お好きな品番をお選びいただけます（AGBS-10-2-HSET2/HSET1/HSET3）"
        ],
        "warnings": [],
        "new_models": [],
        "set_deals": [
          {"name": "セットでお得！(ベルトサンダー10＋ハッピーベルト50本)", "品番": "AGBS-10-2-HSET2 / -HSET1 / -HSET3 (#40/#60/#80)", "セール価格(税抜)": "¥32,000"}
        ]
      },
      {
        "title": "パワーダイヤカッター NEO ／ DORADO-R ／ 低速サンダー76 ／ 超硬カッター",
        "subtitle": "シャープな切れ味！DORADO-R 3+1 SALE 他",
        "table_columns": ["品番", "製品名", "サイズ／仕様", "セール価格(税抜)"],
        "table": [
          {"品番": "DPDKN-100", "製品名": "パワーダイヤカッターNEO（NEW）", "サイズ／仕様": "φ100", "セール価格(税抜)": "¥960"},
          {"品番": "DPDKN-125", "製品名": "パワーダイヤカッターNEO（NEW）", "サイズ／仕様": "φ125", "セール価格(税抜)": "¥1,150"},
          {"品番": "FHR180-3SET", "製品名": "DORADO-R ドラドアール（3+1 SALE）", "サイズ／仕様": "180×1.6×1.1×20 / 結合度45 / 5,500回転", "セール価格(税抜)": "¥12,000"},
          {"品番": "YIG-100S76", "製品名": "低速サンダー76（5枚セット ベベルクィーンパープル/ブラック/グレートブラック/ブラック<パープル>/<黄結>/中目/細目 各2枚）", "サイズ／仕様": "M10ねじ", "セール価格(税抜)": "¥33,000 (YIG-PRO5)"},
          {"品番": "AGSS-ST2-RB8-6SET", "製品名": "ダイグラインダー2 ＋ 超硬カッター 8本組（6mm軸）", "サイズ／仕様": "RB-6SET", "セール価格(税抜)": "¥24,000"}
        ],
        "highlights": [
          "パワーダイヤカッターNEO 新登場！φ100 ¥960／φ125 ¥1,150の特別価格",
          "一般鋼鉄からステンレス、鋼管／薄鉄板、半鉄合金など電線ケーブルからナイロン樹脂、軟質金属（鉛、アルミ、銅）まで幅広く切断",
          "DORADO-R 3+1 SALE — シャープな切れ味の高品質品が¥12,000",
          "低速サンダー76 セット販売品 YIG-PRO5 各2枚で¥33,000",
          "ダイグラインダー2 ＋ 超硬カッター8本組セット ¥24,000"
        ],
        "warnings": [
          "LINEでサクッとお問い合わせ可"
        ],
        "new_models": [
          {"model": "DPDKN-100 / DPDKN-125 パワーダイヤカッターNEO", "note": "NEW（NEOマーク表示）"}
        ]
      }
    ]
  },
  "138": {
    "name": "ヨコタ工業㈱",
    "sources": [
      "グラインダ新リーフレット_p01.png",
      "グラインダ新リーフレット_p02.png"
    ],
    "sections": [
      {
        "title": "High Performance Midget Grinders ／ MG-0A Series",
        "subtitle": "高性能 ミゼットグラインダ — 振れ／衝撃／磨耗に強いミゼット ／ 触れる砥石／超硬ロータリーバー兼用 ／ 芯ブレ精度0.05mm以下の高精度チャック採用 (Decentering: less than 0.05mm)",
        "table_columns": ["Model", "Free Speed", "Air Consumption", "Overall Length", "Weight", "コレット／ホイールサイズ", "Air Inlet Thread", "Air Hose Bore", "Air Pressure", "Sound Level"],
        "table": [
          {"Model": "MG-0AS", "Free Speed": "30,000 min⁻¹", "Air Consumption": "0.45 m³/min", "Overall Length": "165 mm", "Weight": "0.35 kg", "コレット／ホイールサイズ": "—", "Air Inlet Thread": "Rc 1/4", "Air Hose Bore": "8 mm", "Air Pressure": "0.6 MPa", "Sound Level": "82 dB"},
          {"Model": "MG-0AS-1", "Free Speed": "30,000 min⁻¹", "Air Consumption": "0.45 m³/min", "Overall Length": "175 mm", "Weight": "0.40 kg", "コレット／ホイールサイズ": "—", "Air Inlet Thread": "Rc 1/4", "Air Hose Bore": "8 mm", "Air Pressure": "0.6 MPa", "Sound Level": "82 dB"},
          {"Model": "MG-0AS-2", "Free Speed": "30,000 min⁻¹", "Air Consumption": "0.45 m³/min", "Overall Length": "190 mm", "Weight": "0.42 kg", "コレット／ホイールサイズ": "—", "Air Inlet Thread": "Rc 1/4", "Air Hose Bore": "8 mm", "Air Pressure": "0.6 MPa", "Sound Level": "82 dB"},
          {"Model": "MG-0AL", "Free Speed": "20,000 min⁻¹", "Air Consumption": "0.45 m³/min", "Overall Length": "215 mm", "Weight": "0.45 kg", "コレット／ホイールサイズ": "—", "Air Inlet Thread": "Rc 1/4", "Air Hose Bore": "8 mm", "Air Pressure": "0.6 MPa", "Sound Level": "82 dB"},
          {"Model": "MG-0AL-1", "Free Speed": "20,000 min⁻¹", "Air Consumption": "0.45 m³/min", "Overall Length": "225 mm", "Weight": "0.48 kg", "コレット／ホイールサイズ": "—", "Air Inlet Thread": "Rc 1/4", "Air Hose Bore": "8 mm", "Air Pressure": "0.6 MPa", "Sound Level": "82 dB"},
          {"Model": "MG-0AL-2", "Free Speed": "20,000 min⁻¹", "Air Consumption": "0.45 m³/min", "Overall Length": "240 mm", "Weight": "0.50 kg", "コレット／ホイールサイズ": "—", "Air Inlet Thread": "Rc 1/4", "Air Hose Bore": "8 mm", "Air Pressure": "0.6 MPa", "Sound Level": "82 dB"}
        ],
        "highlights": [
          "高性能ミゼットグラインダ — 振れ／衝撃／磨耗に強い高耐久仕様",
          "芯ブレ精度0.05mm以下の高精度チャックを採用（Decentering less than 0.05mm）",
          "触れる砥石／超硬ロータリーバー兼用、現場の研削用途を一台でカバー",
          "ヨコタの空気圧工具らしい軽量・低騒音設計（82dB前後）"
        ],
        "warnings": [
          "数値は代表値であり仕様変更となる場合があります（リーフレット上の機械文字表記より）"
        ],
        "new_models": []
      },
      {
        "title": "Disc Grinders ／ G400H(-S) ／ G700H Series",
        "subtitle": "ディスクグラインダ — スピンドルロック機構搭載 ／ 排出方向可変 (Variable exhaust direction) ／ サイレンサ採用素材 (G400H、G700H) ／ ヘッド部水抜き機構 (Improvement of durability for water suction) ／ 多機能形状の握り、握りすぎを防止するヘッドモーター部",
        "table_columns": ["Model", "Free Speed", "Wheel Size", "Air Consumption", "Overall Length", "Weight", "Air Inlet Thread", "Air Hose Bore", "Air Pressure", "Sound Level"],
        "table": [
          {"Model": "G400H-S", "Free Speed": "11,000 min⁻¹", "Wheel Size": "100 mm", "Air Consumption": "0.85 m³/min", "Overall Length": "—", "Weight": "1.55 kg", "Air Inlet Thread": "Rc 1/4", "Air Hose Bore": "10 mm", "Air Pressure": "0.6 MPa", "Sound Level": "—"},
          {"Model": "G400H", "Free Speed": "11,000 min⁻¹", "Wheel Size": "100 mm", "Air Consumption": "0.85 m³/min", "Overall Length": "—", "Weight": "1.55 kg", "Air Inlet Thread": "Rc 1/4", "Air Hose Bore": "10 mm", "Air Pressure": "0.6 MPa", "Sound Level": "—"},
          {"Model": "G700H", "Free Speed": "7,000 min⁻¹", "Wheel Size": "180 mm", "Air Consumption": "1.20 m³/min", "Overall Length": "—", "Weight": "2.77 kg", "Air Inlet Thread": "Rc 3/8", "Air Hose Bore": "12.7 mm", "Air Pressure": "0.6 MPa", "Sound Level": "—"}
        ],
        "highlights": [
          "ディスクグラインダ G400H/G700Hシリーズ — Light weight, maintaining the output（軽量＆出力両立）",
          "スピンドルロック機構搭載で砥石交換が容易に",
          "排出方向可変（Variable exhaust direction）で作業者への風当たりを軽減",
          "ヘッド部水抜き機構（Improvement of durability for water suction）採用、防水性能向上",
          "G400H-Sはホイールカバー無しサイドハンドル仕様（Wheel cover for cutting wheel）"
        ],
        "warnings": [
          "モーター部の防水仕様は完全防水ではありません",
          "対応砥石の最高使用回転数を必ず確認のこと"
        ],
        "new_models": []
      },
      {
        "title": "Straight Grinders ／ GS-65 Series",
        "subtitle": "ストレートグラインダ GS-65シリーズ — 軽量 (Light weight) 出力を維持しながら軽量・低騒音 ／ 高耐久性 (High durability) モーター部の防水仕様 ／ 多機能形状の握り (Handy power tool)、深部の研削加工に最適",
        "table_columns": ["Model", "Free Speed", "Wheel Size", "Air Consumption", "Overall Length", "Weight", "Air Inlet Thread", "Air Hose Bore", "Air Pressure", "Sound Level"],
        "table": [
          {"Model": "GS-65", "Free Speed": "—", "Wheel Size": "—", "Air Consumption": "—", "Overall Length": "—", "Weight": "—", "Air Inlet Thread": "—", "Air Hose Bore": "—", "Air Pressure": "—", "Sound Level": "—"},
          {"Model": "GS-65L", "Free Speed": "—", "Wheel Size": "—", "Air Consumption": "—", "Overall Length": "—", "Weight": "—", "Air Inlet Thread": "—", "Air Hose Bore": "—", "Air Pressure": "—", "Sound Level": "—"},
          {"Model": "GS-65-C", "Free Speed": "—", "Wheel Size": "—", "Air Consumption": "—", "Overall Length": "—", "Weight": "—", "Air Inlet Thread": "—", "Air Hose Bore": "—", "Air Pressure": "—", "Sound Level": "—"},
          {"Model": "GS-65-L", "Free Speed": "—", "Wheel Size": "—", "Air Consumption": "—", "Overall Length": "—", "Weight": "—", "Air Inlet Thread": "—", "Air Hose Bore": "—", "Air Pressure": "—", "Sound Level": "—"}
        ],
        "highlights": [
          "ストレートグラインダ GS-65シリーズ — 出力を維持しながら軽量・低騒音",
          "モーター部の防水仕様で High durability を実現",
          "多機能形状の握りで深部の研削加工に最適、Handy power tool",
          "リーフレットp02には4タイプ（GS-65 / GS-65L / GS-65-C / GS-65-L）のラインアップを掲載"
        ],
        "warnings": [
          "詳細諸元はカタログ表での確認が必要（画像中の小型表より）"
        ],
        "new_models": []
      }
    ]
  }
}
